TopoMono.cp312-win_amd64.pyd
TopoMono-1.0.dist-info/METADATA
TopoMono-1.0.dist-info/WHEEL
TopoMono-1.0.dist-info/top_level.txt
TopoMono-1.0.dist-info/RECORD
