Metadata-Version: 2.1
Name: TopoMono
Version: 1.0
Summary: TopoMono Module
